python_scrapyd_api-2.1.2.dist-info/DESCRIPTION.rst
python_scrapyd_api-2.1.2.dist-info/METADATA
python_scrapyd_api-2.1.2.dist-info/RECORD
python_scrapyd_api-2.1.2.dist-info/WHEEL
python_scrapyd_api-2.1.2.dist-info/metadata.json
python_scrapyd_api-2.1.2.dist-info/top_level.txt
scrapyd_api/__init__.py
scrapyd_api/client.py
scrapyd_api/compat.py
scrapyd_api/constants.py
scrapyd_api/exceptions.py
scrapyd_api/wrapper.py
