Metadata-Version: 2.1
Name: python-scrapyd-api
Version: 2.1.2
Summary: A Python wrapper for working with the Scrapyd API
Home-page: https://github.com/djm/python-scrapyd-api
Author: Darian Moody
Author-email: mail@djm.org.uk
License: BSD
Keywords: python-scrapyd-api scrapyd scrapy api wrapper
Platform: UNKNOWN
Classifier: Development Status :: 4 - Beta
Classifier: Intended Audience :: Developers
Classifier: License :: OSI Approved :: BSD License
Classifier: Natural Language :: English
Classifier: Programming Language :: Python :: 2
Classifier: Programming Language :: Python :: 2.6
Classifier: Programming Language :: Python :: 2.7
Classifier: Programming Language :: Python :: 3
Classifier: Programming Language :: Python :: 3.3
Classifier: Programming Language :: Python :: 3.4
Classifier: Topic :: Internet :: WWW/HTTP
